packagify/__init__.py
packagify-1.2.dist-info/LICENSE
packagify-1.2.dist-info/METADATA
packagify-1.2.dist-info/WHEEL
packagify-1.2.dist-info/top_level.txt
packagify-1.2.dist-info/RECORD
