Metadata-Version: 2.1
Name: packagify
Version: 1.2
Summary: A packaging utility to treat folders as packages
Home-page: https://github.com/rijulg/packagify
Download-URL: https://github.com/rijulg/packagify/archive/v1.2.tar.gz
Author: Rijul Gupta
Author-email: rijulg@gmail.com
License: MIT
Keywords: Packaging,Helper
Classifier: Development Status :: 4 - Beta
Classifier: Intended Audience :: Developers
Classifier: License :: OSI Approved :: MIT License
Classifier: Operating System :: OS Independent
Classifier: Topic :: Utilities
License-File: LICENSE
